{
  "SheetType": "Character",
  "RaceType": "Heteromorph",
  "SheetNum": 24,
  "RomanjiName1": "Entoma",
  "RomanjiName2": "Vasilissa Zeta (ζ)",
  "RomanjiSecondaryName": "",
  "HiraganaName": "エントマ・ヴァシリッサ・ゼータ",
  "HiraganaSecondaryName": "",
  "Epithet1": "The bug-loving Battle Maid",
  "Epithet2": "",
  "Epithet3": "",
  "Position1": "One of the Pleiades Battle Maids of the Great",
  "Position2": "Underground Tomb of Nazarick",
  "Residence1": "The servants' quarters on the 9th Floor of the",
  "Residence2": "Great Underground Tomb of Nazarick",
  "AlignmentText": "Neutral Evil",
  "KarmaValue": -100,
  "VisibleRacialClasses": 1,
  "RaceClass1": "Arachnoid",
  "RaceClass2": "",
  "RaceClass3": "",
  "RaceClass4": "",
  "RaceClass5": "",
  "RaceClass6": "",
  "RaceClass7": "",
  "RaceClass8": "",
  "VisibleJobClasses": 4,
  "JobClass1": "Talismancer",
  "JobClass2": "Throwing Talisman Specialist",
  "JobClass3": "Entomancer",
  "JobClass4": "Weapon Master",
  "JobClass5": "",
  "JobClass6": "",
  "JobClass7": "",
  "JobClass8": "",
  "RaceLevel1": 10,
  "RaceLevel2": 0,
  "RaceLevel3": 0,
  "RaceLevel4": 0,
  "RaceLevel5": 0,
  "RaceLevel6": 0,
  "RaceLevel7": 0,
  "RaceLevel8": 0,
  "JobLevel1": 10,
  "JobLevel2": 7,
  "JobLevel3": 7,
  "JobLevel4": 3,
  "JobLevel5": 0,
  "JobLevel6": 0,
  "JobLevel7": 0,
  "JobLevel8": 0,
  "RaceOthers": true,
  "JobOthers": true,
  "TotalLevels": 51,
  "TotalRaceLevels": 12,
  "TotalJobLevels": 39,
  "HP": 43,
  "MP": 31,
  "PhysicalAttack": 32,
  "PhysicalDefense": 30,
  "Agility": 33,
  "MagicAttack": 36,
  "MagicDefense": 35,
  "Resistance": 33,
  "Special": 41,
  "CharacterXpos": 0,
  "CharacterYpos": 0,
  "CharacterWidth": 0,
  "CharacterHeight": 0,
  "CharacterImageName": "24-Entoma.jpg",
  "TemplateImageName": "Heteromorph-Demihuman.png"
}